{
    "name": "slide",
    "author": "MegaRataRex",
    "description": "xd",
    "emote":{
        "isLoop": "false",
        "returnTick": 2,
        "beginTick":1,
        "endTick":5,
        "stopTick":11,
        "degrees":false,
        "moves":[
            
            {
                "tick":1,
                "easing": "EASEINOUTQUAD",
                "turn": 0,
                "torso":{
                    "pitch":-0.04556630551815033
                }
            },
            {
                "tick":5,
                "easing": "EASEINOUTQUAD",
                "turn": 0,
                "torso":{
                    "pitch":0.27801668643951416
                }
            },
            {
                "tick":4,
                "easing": "EASEINOUTQUAD",
                "turn": 0,
                "torso":{
                    "y":-0.130514994263649
                }
            },
            {
                "tick":5,
                "easing": "EASEINOUTQUAD",
                "turn": 0,
                "torso":{
                    "y":-0.9371442198753357
                }
            },
            {
                "tick":5,
                "easing": "EASEINOUTQUAD",
                "turn": 0,
                "torso":{
                    "x":0.0
                }
            },
            {
                "tick":5,
                "easing": "EASEINOUTQUAD",
                "turn": 0,
                "torso":{
                    "z":-0.0
                }
            },
            {
                "tick":1,
                "easing": "EASEINOUTQUAD",
                "turn": 0,
                "torso":{
                    "bend":0.10327614098787308
                }
            },
            {
                "tick":5,
                "easing": "EASEINOUTQUAD",
                "turn": 0,
                "torso":{
                    "bend":0.2960592806339264
                }
            },
            {
                "tick":1,
                "easing": "EASEINOUTQUAD",
                "turn": 0,
                "rightArm":{
                    "pitch":0.2321929931640625
                }
            },
            {
                "tick":5,
                "easing": "EASEINOUTQUAD",
                "turn": 0,
                "rightArm":{
                    "pitch":-1.6414785385131836
                }
            },
            {
                "tick":1,
                "easing": "EASEINOUTQUAD",
                "turn": 0,
                "rightArm":{
                    "bend":-0.3112478256225586
                }
            },
            {
                "tick":5,
                "easing": "EASEINOUTQUAD",
                "turn": 0,
                "rightArm":{
                    "bend":-0.00674302875995636
                }
            },
            {
                "tick":1,
                "easing": "EASEINOUTQUAD",
                "turn": 0,
                "leftArm":{
                    "pitch":0.21188543736934662
                }
            },
            {
                "tick":5,
                "easing": "EASEINOUTQUAD",
                "turn": 0,
                "leftArm":{
                    "pitch":1.2548879384994507
                }
            },
            {
                "tick":1,
                "easing": "EASEINOUTQUAD",
                "turn": 0,
                "leftArm":{
                    "bend":-0.16936245560646057
                }
            },
            {
                "tick":5,
                "easing": "EASEINOUTQUAD",
                "turn": 0,
                "leftArm":{
                    "bend":-1.638758897781372
                }
            },
            {
                "tick":1,
                "easing": "EASEINOUTQUAD",
                "turn": 0,
                "rightLeg":{
                    "pitch":-0.22469811141490936
                }
            },
            {
                "tick":5,
                "easing": "EASEINOUTQUAD",
                "turn": 0,
                "rightLeg":{
                    "pitch":-1.3453879356384277
                }
            },
            {
                "tick":5,
                "easing": "EASEINOUTQUAD",
                "turn": 0,
                "rightLeg":{
                    "y":10.418009757995605
                }
            },
            {
                "tick":5,
                "easing": "EASEINOUTQUAD",
                "turn": 0,
                "rightLeg":{
                    "z":-0.3515129923820496
                }
            },
            {
                "tick":1,
                "easing": "EASEINOUTQUAD",
                "turn": 0,
                "rightLeg":{
                    "bend":0.15839315950870514
                }
            },
            {
                "tick":5,
                "easing": "EASEINOUTQUAD",
                "turn": 0,
                "rightLeg":{
                    "bend":0.10945898294448853
                }
            },
            {
                "tick":1,
                "easing": "EASEINOUTQUAD",
                "turn": 0,
                "leftLeg":{
                    "pitch":-0.1908884197473526
                }
            },
            {
                "tick":5,
                "easing": "EASEINOUTQUAD",
                "turn": 0,
                "leftLeg":{
                    "pitch":-1.3769621849060059
                }
            },
            {
                "tick":5,
                "easing": "EASEINOUTQUAD",
                "turn": 0,
                "leftLeg":{
                    "y":9.453656673431396
                }
            },
            {
                "tick":5,
                "easing": "EASEINOUTQUAD",
                "turn": 0,
                "leftLeg":{
                    "z":-0.8267473340034485
                }
            },
            {
                "tick":1,
                "easing": "EASEINOUTQUAD",
                "turn": 0,
                "leftLeg":{
                    "bend":0.14176057279109955
                }
            },
            {
                "tick":5,
                "easing": "EASEINOUTQUAD",
                "turn": 0,
                "leftLeg":{
                    "bend":0.23151034116744995
                }
            }
        ]
    }
}